yai_nexus_api_middleware/__init__.py
yai_nexus_api_middleware/builder.py
yai_nexus_api_middleware/dependencies.py
yai_nexus_api_middleware/models.py
yai_nexus_api_middleware/responses.py
yai_nexus_api_middleware/internal/core_middleware.py
yai_nexus_api_middleware-0.1.1.dist-info/METADATA
yai_nexus_api_middleware-0.1.1.dist-info/WHEEL
yai_nexus_api_middleware-0.1.1.dist-info/RECORD
