Metadata-Version: 2.4
Name: yai-nexus-api-middleware
Version: 0.1.1
Summary: FastAPI middleware for Y-AI Nexus
Project-URL: Homepage, https://github.com/your-org/yai-nexus-api-middleware
Project-URL: Bug Tracker, https://github.com/your-org/yai-nexus-api-middleware/issues
Author-email: Y-AI Nexus <dev@y-ai.ltd>
License-Expression: MIT
Classifier: Framework :: FastAPI
Classifier: License :: OSI Approved :: MIT License
Classifier: Operating System :: OS Independent
Classifier: Programming Language :: Python :: 3
Requires-Python: >=3.10
Requires-Dist: fastapi>=0.100.0
Requires-Dist: pydantic>=2.0.0
Requires-Dist: yai-nexus-logger==0.2.2
Provides-Extra: dev
Requires-Dist: httpx>=0.24.0; extra == 'dev'
Requires-Dist: pytest>=7.0.0; extra == 'dev'
Requires-Dist: uvicorn[standard]>=0.20.0; extra == 'dev'
